{
    "os": "Linux-5.15.0-117-generic-x86_64-with-glibc2.29",
    "python": "3.8.10",
    "heartbeatAt": "2024-08-19T03:31:18.968616",
    "startedAt": "2024-08-19T03:31:18.118263",
    "docker": null,
    "cuda": null,
    "args": [],
    "state": "running",
    "program": "/home/chkim/HGGD/my_test.py",
    "codePathLocal": "my_test.py",
    "codePath": "my_test.py",
    "git": {
        "remote": "https://github.com/Kim-chan186/GRASP.git",
        "commit": "877f0f8ab8aee348546c4d107ad00594b097527c"
    },
    "email": "kch1051104@naver.com",
    "root": "/home/chkim/HGGD",
    "host": "chkim",
    "username": "chkim",
    "executable": "/bin/python3",
    "cpu_count": 12,
    "cpu_count_logical": 20,
    "cpu_freq": {
        "current": 2094.6830999999997,
        "min": 800.0,
        "max": 4580.0
    },
    "cpu_freq_per_core": [
        {
            "current": 2100.0,
            "min": 800.0,
            "max": 4800.0
        },
        {
            "current": 2100.0,
            "min": 800.0,
            "max": 4800.0
        },
        {
            "current": 2100.0,
            "min": 800.0,
            "max": 4800.0
        },
        {
            "current": 2100.0,
            "min": 800.0,
            "max": 4800.0
        },
        {
            "current": 2100.0,
            "min": 800.0,
            "max": 4900.0
        },
        {
            "current": 2100.0,
            "min": 800.0,
            "max": 4900.0
        },
        {
            "current": 2100.0,
            "min": 800.0,
            "max": 4900.0
        },
        {
            "current": 2100.0,
            "min": 800.0,
            "max": 4900.0
        },
        {
            "current": 834.467,
            "min": 800.0,
            "max": 4800.0
        },
        {
            "current": 2100.0,
            "min": 800.0,
            "max": 4800.0
        },
        {
            "current": 2100.0,
            "min": 800.0,
            "max": 4800.0
        },
        {
            "current": 2100.0,
            "min": 800.0,
            "max": 4800.0
        },
        {
            "current": 2100.0,
            "min": 800.0,
            "max": 4800.0
        },
        {
            "current": 2100.0,
            "min": 800.0,
            "max": 4800.0
        },
        {
            "current": 2100.0,
            "min": 800.0,
            "max": 4800.0
        },
        {
            "current": 2100.0,
            "min": 800.0,
            "max": 4800.0
        },
        {
            "current": 2100.0,
            "min": 800.0,
            "max": 3600.0
        },
        {
            "current": 2100.0,
            "min": 800.0,
            "max": 3600.0
        },
        {
            "current": 2100.0,
            "min": 800.0,
            "max": 3600.0
        },
        {
            "current": 2100.0,
            "min": 800.0,
            "max": 3600.0
        }
    ],
    "disk": {
        "/": {
            "total": 915.3232879638672,
            "used": 434.2452621459961
        }
    },
    "gpu": "NVIDIA TITAN Xp",
    "gpu_count": 1,
    "gpu_devices": [
        {
            "name": "NVIDIA TITAN Xp",
            "memory_total": 12884901888
        }
    ],
    "memory": {
        "total": 31.179676055908203
    }
}
